{
  "spec_id": "DE-V2-GOV-02",
  "diagram_levels": {
    "L1": "System Context",
    "L2": "Containers (7-Layer Polyglot)",
    "L3": "Data Flow Protocols"
  },
  "technologies": [
    "NATS JetStream",
    "Apache Arrow",
    "gRPC",
    "Protobuf",
    "Elixir/OTP",
    "Go",
    "Python",
    "Rust",
    "Zig",
    "Mojo",
    "Tauri/TS"
  ],
  "invariants": [
    "Every container must have a layer assignment (L0-L6)",
    "Every inter-container relation must specify a protocol",
    "Diagrams must use C4 naming conventions (Person, System, Container, Rel)"
  ],
  "personality_ref": "DE-V2-L0-33"
}
