{
  "spec_id": "DE-V2-L3-47",
  "domain": "L3_Secrets",
  "vault_policy": {
    "storage_enclave": "L3_Rust_Vault",
    "injection_method": "Placeholder_Hydration",
    "forbidden_patterns": ["REAL_KEY_IN_CONTEXT", "UNMASKED_LOGGING"]
  },
  "secret_lifecycle": {
    "request": "Placeholder ($VAULT_*)",
    "hydration_points": ["L1_Nervous_Adapter", "L5_Integration_Adapter"]
  },
  "scrubbing": {
    "auto_redact": true,
    "entropy_threshold": 4.5,
    "mandatory_log_audit": true
  },
  "invariants": {
    "no_raw_secrets_in_context": true,
    "scope_based_access_only": true
  },
  "enforcement": "STRICT_BLOCK",
  "personality_ref": "DE-V2-L0-33"
}
